{"extVersion":"1.29.8","name":"OWS - Recorders","icon":"riGlobalLine","table":[],"version":"1.28.27","drawflow":{"edges":[{"data":{},"events":{},"id":"vZPHqtYUAq2byUZtieCmf","markerEnd":"arrowclosed","selectable":true,"source":"tCMZhtXMwhcInLYt-QN_b","sourceHandle":"tCMZhtXMwhcInLYt-QN_b-output-1","sourceX":262,"sourceY":336,"target":"d2mn9ByfTYh5DnQcNLHWV","targetHandle":"d2mn9ByfTYh5DnQcNLHWV-input-1","targetX":300,"targetY":336,"type":"custom","updatable":true},{"data":{},"events":{},"id":"seqzyBDceSZzw-Jm0pdlk","markerEnd":"arrowclosed","selectable":true,"source":"d2mn9ByfTYh5DnQcNLHWV","sourceHandle":"d2mn9ByfTYh5DnQcNLHWV-output-1","sourceX":532,"sourceY":336,"target":"_PxmjgFcZrO0juzNaxRkU","targetHandle":"_PxmjgFcZrO0juzNaxRkU-input-1","targetX":580,"targetY":336,"type":"custom","updatable":true},{"data":{},"events":{},"id":"Q5JlL1Jlssy1m8ySQBw0j","markerEnd":"arrowclosed","selectable":true,"source":"_PxmjgFcZrO0juzNaxRkU","sourceHandle":"_PxmjgFcZrO0juzNaxRkU-output-1","sourceX":812,"sourceY":336,"target":"b5Lqt_SS0W6CqUOdHgfNz","targetHandle":"b5Lqt_SS0W6CqUOdHgfNz-input-1","targetX":860,"targetY":336,"type":"custom","updatable":true},{"data":{},"events":{},"id":"nYqcrU_ENa0ZMaDxYMcEz","markerEnd":"arrowclosed","selectable":true,"source":"b5Lqt_SS0W6CqUOdHgfNz","sourceHandle":"b5Lqt_SS0W6CqUOdHgfNz-output-1","sourceX":1092,"sourceY":336,"target":"ikCewGHnpjemcccoBtYsB","targetHandle":"ikCewGHnpjemcccoBtYsB-input-1","targetX":1140,"targetY":336,"type":"custom","updatable":true},{"data":{},"events":{},"id":"d4xN7RXBnzXJ409HAGyXE","markerEnd":"arrowclosed","selectable":true,"source":"ikCewGHnpjemcccoBtYsB","sourceHandle":"ikCewGHnpjemcccoBtYsB-output-1","sourceX":1372,"sourceY":336,"target":"IafH4DsNGOekPmoBAx5FD","targetHandle":"IafH4DsNGOekPmoBAx5FD-input-1","targetX":1420,"targetY":336,"type":"custom","updatable":true},{"data":{},"events":{},"id":"FX2CZaW8EuDwPTwLPgOCH","markerEnd":"arrowclosed","selectable":true,"source":"IafH4DsNGOekPmoBAx5FD","sourceHandle":"IafH4DsNGOekPmoBAx5FD-output-1","sourceX":1652,"sourceY":336,"target":"L_7AfYSA1opYbACaoD9Rm","targetHandle":"L_7AfYSA1opYbACaoD9Rm-input-1","targetX":30,"targetY":486,"type":"custom","updatable":true},{"data":{},"events":{},"id":"K4di3q-lrK3FyUy8VuoMw","markerEnd":"arrowclosed","selectable":true,"source":"L_7AfYSA1opYbACaoD9Rm","sourceHandle":"L_7AfYSA1opYbACaoD9Rm-output-1","sourceX":262,"sourceY":486,"target":"xs7Rz1UwlhVWT94ieAVUf","targetHandle":"xs7Rz1UwlhVWT94ieAVUf-input-1","targetX":310,"targetY":486,"type":"custom","updatable":true},{"class":"source-xs7Rz1UwlhVWT94ieAVUf-output-1 target-t-YvE4kbaPQZ8IwMmQrz4-input-1","data":{},"events":{},"id":"vueflow__edge-xs7Rz1UwlhVWT94ieAVUfxs7Rz1UwlhVWT94ieAVUf-output-1-t-YvE4kbaPQZ8IwMmQrz4t-YvE4kbaPQZ8IwMmQrz4-input-1","markerEnd":"arrowclosed","selectable":true,"source":"xs7Rz1UwlhVWT94ieAVUf","sourceHandle":"xs7Rz1UwlhVWT94ieAVUf-output-1","sourceX":542,"sourceY":486,"target":"t-YvE4kbaPQZ8IwMmQrz4","targetHandle":"t-YvE4kbaPQZ8IwMmQrz4-input-1","targetX":590,"targetY":486,"type":"custom","updatable":true},{"class":"connected-edges","data":{},"events":{},"id":"vueflow__edge-t-YvE4kbaPQZ8IwMmQrz4t-YvE4kbaPQZ8IwMmQrz4-output-1-tff9vkmtff9vkm-input-1","markerEnd":"arrowclosed","selectable":true,"source":"t-YvE4kbaPQZ8IwMmQrz4","sourceHandle":"t-YvE4kbaPQZ8IwMmQrz4-output-1","sourceX":822,"sourceY":486,"target":"tff9vkm","targetHandle":"tff9vkm-input-1","targetX":899,"targetY":485,"type":"custom","updatable":true}],"nodes":[{"data":{"activeInInput":false,"contextMenuName":"","contextTypes":[],"date":"","days":[],"delay":5,"description":"","disableBlock":false,"interval":60,"isUrlRegex":false,"observeElement":{"baseElOptions":{"attributeFilter":[],"attributes":false,"characterData":false,"childList":true,"subtree":false},"baseSelector":"","matchPattern":"","selector":"","targetOptions":{"attributeFilter":[],"attributes":false,"characterData":false,"childList":true,"subtree":false}},"parameters":[],"preferParamsInTab":false,"shortcut":"","time":"00:00","triggers":[{"data":{"activeInInput":false,"contextMenuName":"","contextTypes":[],"date":"","days":[],"delay":5,"description":"","disableBlock":false,"interval":60,"isUrlRegex":false,"observeElement":{"baseElOptions":{"attributeFilter":[],"attributes":false,"characterData":false,"childList":true,"subtree":false},"baseSelector":"","matchPattern":"","selector":"","targetOptions":{"attributeFilter":[],"attributes":false,"characterData":false,"childList":true,"subtree":false}},"parameters":[],"preferParamsInTab":false,"shortcut":"","time":"00:00","type":"manual","url":""},"id":"BLeOy","type":"manual"},{"data":{"isUrlRegex":false,"supportSPA":false,"url":"https://ows.openeye.net/recorders"},"id":"yECzs","type":"visit-web"}],"type":"manual","url":""},"events":{},"id":"tCMZhtXMwhcInLYt-QN_b","label":"trigger","position":{"x":50,"y":300},"type":"BlockBasic"},{"data":{"active":true,"customUserAgent":false,"description":"","disableBlock":true,"inGroup":false,"tabZoom":1,"updatePrevTab":false,"url":"https://ows.openeye.net/recorders/connect?cm=Z6W49F&s=&sort=","userAgent":"","waitTabLoaded":false},"events":{},"id":"d2mn9ByfTYh5DnQcNLHWV","label":"new-tab","position":{"x":320,"y":300},"type":"BlockBasic"},{"data":{"assignVariable":false,"clearValue":true,"dataColumn":"","delay":100,"description":"Text field ()","disableBlock":false,"events":[],"findBy":"cssSelector","getValue":false,"markEl":false,"multiple":false,"optionPosition":"1","saveData":false,"selectOptionBy":"value","selected":true,"selector":"input.MuiInputBase-input","type":"text-field","value":"Spanish Springs Mini Storage","variableName":"","waitForSelector":true,"waitSelectorTimeout":5000},"events":{},"id":"_PxmjgFcZrO0juzNaxRkU","label":"forms","position":{"x":600,"y":300},"type":"BlockBasic"},{"data":{"description":"","disableBlock":true,"findBy":"cssSelector","incX":false,"incY":false,"markEl":false,"multiple":false,"scrollIntoView":false,"scrollX":3,"scrollY":0,"selector":"input.MuiInputBase-input","smooth":true,"waitForSelector":false,"waitSelectorTimeout":5000},"events":{},"id":"b5Lqt_SS0W6CqUOdHgfNz","label":"element-scroll","position":{"x":880,"y":300},"type":"BlockBasic"},{"data":{"description":"CONNECT","disableBlock":false,"findBy":"cssSelector","markEl":false,"multiple":false,"selector":"span.k-button-text","waitForSelector":true,"waitSelectorTimeout":5000},"events":{},"id":"ikCewGHnpjemcccoBtYsB","label":"event-click","position":{"x":1160,"y":300},"type":"BlockBasic"},{"data":{"description":"","disableBlock":true,"findBy":"cssSelector","incX":false,"incY":false,"markEl":false,"multiple":false,"scrollIntoView":false,"scrollX":0,"scrollY":0,"selector":"input.MuiInputBase-input","smooth":true,"waitForSelector":false,"waitSelectorTimeout":5000},"events":{},"id":"IafH4DsNGOekPmoBAx5FD","label":"element-scroll","position":{"x":1440,"y":300},"type":"BlockBasic"},{"data":{"active":true,"customUserAgent":false,"description":"","disableBlock":true,"inGroup":false,"tabZoom":1,"updatePrevTab":true,"url":"https://edrfb7cv54w8furqhenrjzehe-35-92-236-55.us-w2.u5fgb.com/?rhttp2pd=false&rhttpd=Z6WXU1&rhttpm=a&rhttpok=op&rhttph=ows.openeye.net&rhttpv=2&_csrf=HUTX9FHEMVJQ4&rhttpcm=Z6W49F&disableTopNavBar=false","userAgent":"","waitTabLoaded":false},"events":{},"id":"L_7AfYSA1opYbACaoD9Rm","label":"new-tab","position":{"x":50,"y":450},"type":"BlockBasic"},{"data":{"active":true,"customUserAgent":false,"description":"","disableBlock":true,"inGroup":false,"tabZoom":1,"updatePrevTab":true,"url":"https://edrfb7cv54w8furqhenrjzehe-35-92-236-55.us-w2.u5fgb.com/live","userAgent":"","waitTabLoaded":false},"events":{},"id":"xs7Rz1UwlhVWT94ieAVUf","label":"new-tab","position":{"x":330,"y":450},"type":"BlockBasic"},{"data":{"description":" Buck Companies  Spanish","disableBlock":false,"findBy":"cssSelector","markEl":false,"multiple":false,"selector":"html","waitForSelector":true,"waitSelectorTimeout":5000},"events":{},"id":"t-YvE4kbaPQZ8IwMmQrz4","label":"event-click","position":{"x":610,"y":450},"type":"BlockBasic"},{"data":{"description":"","disableBlock":true,"findBy":"cssSelector","markEl":false,"multiple":false,"selector":"div.oe-cloud-breadcrumb-bar","waitForSelector":false,"waitSelectorTimeout":5000},"events":{},"id":"tff9vkm","label":"hover-element","position":{"x":919,"y":449},"type":"BlockBasic"}],"position":[16.42121595218947,97.57148603608783],"viewport":{"x":16.42121595218947,"y":97.57148603608783,"zoom":0.5643029536834846},"zoom":0.5643029536834846},"settings":{"blockDelay":2000,"debugMode":false,"defaultColumnName":"column","execContext":"popup","executedBlockOnWeb":false,"inputAutocomplete":true,"insertDefaultColumn":false,"notification":true,"onError":"stop-workflow","publicId":"","restartTimes":3,"reuseLastState":false,"saveLog":true,"tabLoadTimeout":30000},"globalData":"{\n\t\"key\": \"value\"\n}","description":"","includedWorkflows":{}}